{
  "default": "v0.12.0",
  "v0.12.0": {
    "win32": {
      "enclose": {
        "name": "enclose-v0.12.0-win32-6616e7f.exe",
        "size": 8351634,
        "shasum": "358d7cc8f416d052a9d25cb236526f2a2ad4605d",
        "location": "http://enclosejs.s3.amazonaws.com/enclose-v0.12.0-win32-6616e7f.exe"
      },
      "mksnapshot": {
        "name": "mksnapshot-v0.12.0-win32-6616e7f.exe",
        "size": 3752448,
        "shasum": "7bd36d1151623786e333e8d1dc9da5b0daf7d961",
        "location": "http://enclosejs.s3.amazonaws.com/mksnapshot-v0.12.0-win32-6616e7f.exe"
      }
    },
    "win64": {
      "enclose": {
        "name": "enclose-v0.12.0-win64-6616e7f.exe",
        "size": 10062248,
        "shasum": "5ce468d11d750532f4803a3348f65b62d6daaa57",
        "location": "http://enclosejs.s3.amazonaws.com/enclose-v0.12.0-win64-6616e7f.exe"
      },
      "mksnapshot": {
        "name": "mksnapshot-v0.12.0-win64-6616e7f.exe",
        "size": 4486144,
        "shasum": "708a502af018c18dace8af0d69c982bc2dca5630",
        "location": "http://enclosejs.s3.amazonaws.com/mksnapshot-v0.12.0-win64-6616e7f.exe"
      }
    },
    "linux-x64": {
      "enclose": {
        "name": "enclose-v0.12.0-linux-x64-6616e7f",
        "size": 14327811,
        "shasum": "ad13f931ba210bdf33a9c54977f4da31e211ecb6",
        "location": "http://enclosejs.s3.amazonaws.com/enclose-v0.12.0-linux-x64-6616e7f"
      },
      "mksnapshot": {
        "name": "mksnapshot-v0.12.0-linux-x64-6616e7f",
        "size": 7666840,
        "shasum": "8be8446df66cf60c5e164d2dda9e5f712b801d9e",
        "location": "http://enclosejs.s3.amazonaws.com/mksnapshot-v0.12.0-linux-x64-6616e7f"
      }
    },
    "linux-x86": {
      "enclose": {
        "name": "enclose-v0.12.0-linux-x86-6616e7f",
        "size": 13794023,
        "shasum": "f0bde54e489d11c590cbd9fe050e59cd40e0da19",
        "location": "http://enclosejs.s3.amazonaws.com/enclose-v0.12.0-linux-x86-6616e7f"
      },
      "mksnapshot": {
        "name": "mksnapshot-v0.12.0-linux-x86-6616e7f",
        "size": 7664732,
        "shasum": "9626ba91b727874cefd5d976411be5fe28a76e50",
        "location": "http://enclosejs.s3.amazonaws.com/mksnapshot-v0.12.0-linux-x86-6616e7f"
      }
    }
  },
  "v1.1.0": {
    "win32": {
      "enclose": {
        "name": "enclose-v1.1.0-win32-6616e7f.exe",
        "size": 9182490,
        "shasum": "5ea740ae7b7740134199f376c4306c270c2d361c",
        "location": "http://enclosejs.s3.amazonaws.com/enclose-v1.1.0-win32-6616e7f.exe"
      },
      "mksnapshot": {
        "name": "mksnapshot-v1.1.0-win32-6616e7f.exe",
        "size": 4233216,
        "shasum": "21b2ab9ef1f1a19eb1c85b033be9f0dffefe1070",
        "location": "http://enclosejs.s3.amazonaws.com/mksnapshot-v1.1.0-win32-6616e7f.exe"
      }
    },
    "win64": {
      "enclose": {
        "name": "enclose-v1.1.0-win64-6616e7f.exe",
        "size": 11666786,
        "shasum": "f45f4223ee3a2a77af1b714e5bb486aa0b8df180",
        "location": "http://enclosejs.s3.amazonaws.com/enclose-v1.1.0-win64-6616e7f.exe"
      },
      "mksnapshot": {
        "name": "mksnapshot-v1.1.0-win64-6616e7f.exe",
        "size": 5285888,
        "shasum": "0b9d9364749fcb6b2ada966c1a3686db99171cef",
        "location": "http://enclosejs.s3.amazonaws.com/mksnapshot-v1.1.0-win64-6616e7f.exe"
      }
    },
    "linux-x64": {
      "enclose": {
        "name": "enclose-v1.1.0-linux-x64-6616e7f",
        "size": 16325490,
        "shasum": "4c8af333511001fdac821aaaef7ab9954f3be577",
        "location": "http://enclosejs.s3.amazonaws.com/enclose-v1.1.0-linux-x64-6616e7f"
      },
      "mksnapshot": {
        "name": "mksnapshot-v1.1.0-linux-x64-6616e7f",
        "size": 8814928,
        "shasum": "4acc638a879631a5b351e19f1af333c19ddcb2c8",
        "location": "http://enclosejs.s3.amazonaws.com/mksnapshot-v1.1.0-linux-x64-6616e7f"
      }
    }
  }
}